{
  "_id": "RandomUniqueID-EG-DyeAnotherDay",
  "areaType": 2,
  "requirements": [
    {
      "areaType": 2,
      "requiredLevel": 1,
      "type": "Area"
    },
    {
      "templateId": "5b3f16c486f7747c327f55f7",
      "count": 1,
      "isFunctional": false,
      "type": "Item"
    },
    {
      "templateId": "5f60e7788adaa7100c3adb49",
      "count": 1,
      "isFunctional": false,
      "type": "Item"
    },
    {
      "templateId": "5c13cd2486f774072c757944",
      "count": 1,
      "isFunctional": false,
      "type": "Item"
    }
  ],
  "productionTime": 7800,
  "endProduct": "5b3f3af486f774679e752c1f",
  "continuous": false,
  "count": 1,
  "productionLimitCount": 0
}